aws_report_generator/__init__.py
aws_report_generator/config.py
aws_report_generator/models.py
aws_report_generator/utils.py
23303395_aws_report_generator-0.1.0.dist-info/METADATA
23303395_aws_report_generator-0.1.0.dist-info/WHEEL
23303395_aws_report_generator-0.1.0.dist-info/top_level.txt
23303395_aws_report_generator-0.1.0.dist-info/RECORD
